{
 "base_power": {
  "Clay": 1,
  "Ninsun, Mother of Gilgamesh": 2,
  "Alewife Siduri": 2,
  "Trapper": 2,
  "Gilgamesh": 0,
  "Enkidu": 0,
  "Shamhat": 3,
  "Ferryman Urshanabi": 4,
  "Mountain Lions": 2,
  "Scorpion-Men": 4,
  "The Serpent": 5,
  "Ishtar": 8,
  "Utnapishtim, Survivor of the Flood": 8,
  "Humbaba, Guardian of the Cedar Forest": 7,
  "Bull of Heaven": 9,
  "\u0160ara, Inanna's Beautician": 3,
  "Kur-Jara": 3,
  "Gala-Tura": 2,
  "Gatekeeper Neti": 4,
  "Nin\u0161ubur, Sukkal to Inanna": 5,
  "Galla Demons": 5,
  "Geshtinanna, Dumuzid's Sister": 5,
  "Sirtur, Mourning Mother": 4,
  "Dirt under Enki's Fingernail": 4,
  "Underworld Courier": 7,
  "Inanna, Goddess of Love and War": 6,
  "Dumuzid, Shepherd God": 8,
  "Lulal, Inanna's Bodyguard": 5,
  "Namtar, Sukkal to Ereshkigal": 8,
  "Anunnaki, The Seven Judges": 8,
  "The Great Sumerian Deluge": 0,
  "Craftsmen of the Ark": 7,
  "Flies": 2,
  "Slave": 3,
  "Shepherd": 2,
  "Farmer": 3,
  "Fisherman": 5,
  "Sacrificer at the Altar": 5,
  "Weeping Mother Goddess": 5,
  "Shipbuilder": 5,
  "Citizen of Shruppak": 5,
  "Elders of Shuruppak": 1,
  "Atrahasis, Flood Survivor": 8,
  "Enlil, Storm God": 8,
  "The Ark": 15,
  "Eurybates, Herald of Odysseus": 3,
  "Calchas, Prophet of Apollo": 3,
  "Sinon the Deceiver": -1,
  "Greek Soldiers": 3,
  "Dolon the Scout": -1,
  "Menelaus, the Wronged King": 3,
  "Camp Guard at the Ships": 5,
  "Epeius, Builder of the Horse": 4,
  "Odysseus": 6,
  "Patroclus": 6,
  "The Trojan Horse": -1,
  "Ajax, the Great": 8,
  "Agamemnon, King of Mycenae": 7,
  "Achilles": 8,
  "Diomedes, the God-Smiter": 8
 },
 "tweaks": {
  "Calchas, Prophet of Apollo": 2,
  "Gatekeeper Neti": 3,
  "Inanna, Goddess of Love and War": 7,
  "Kur-Jara": 2,
  "\u0160ara, Inanna's Beautician": 2
 },
 "history": [
  {
   "iteration": 1,
   "accepted": "\u0160ara, Inanna's Beautician: power 3 -> 2",
   "objective": 0.03859066348046904,
   "deck_term": 0.020073760550481417,
   "card_term": 0.018516902929987616,
   "win_rates": {
    "epic_of_gilgamesh": 0.46766169154228854,
    "inannas_descent": 0.6169154228855721,
    "the_flood": 0.42786069651741293,
    "siege_of_troy": 0.48756218905472637
   }
  },
  {
   "iteration": 2,
   "accepted": "Kur-Jara: power 3 -> 2",
   "objective": 0.035931833997096846,
   "deck_term": 0.01705403331600703,
   "card_term": 0.01887780068108982,
   "win_rates": {
    "epic_of_gilgamesh": 0.5074626865671642,
    "inannas_descent": 0.5870646766169154,
    "the_flood": 0.40298507462686567,
    "siege_of_troy": 0.5024875621890548
   }
  },
  {
   "iteration": 3,
   "accepted": "Inanna, Goddess of Love and War: power 6 -> 7",
   "objective": 0.01877834007217195,
   "deck_term": 0.0017078785178584709,
   "card_term": 0.01707046155431348,
   "win_rates": {
    "epic_of_gilgamesh": 0.48756218905472637,
    "inannas_descent": 0.5323383084577115,
    "the_flood": 0.5024875621890548,
    "siege_of_troy": 0.47761194029850745
   }
  },
  {
   "iteration": 4,
   "accepted": "Gatekeeper Neti: power 4 -> 3",
   "objective": 0.025069123099062986,
   "deck_term": 0.010321526694883789,
   "card_term": 0.014747596404179195,
   "win_rates": {
    "epic_of_gilgamesh": 0.4577114427860697,
    "inannas_descent": 0.5621890547263682,
    "the_flood": 0.4427860696517413,
    "siege_of_troy": 0.5373134328358209
   }
  },
  {
   "iteration": 5,
   "accepted": "Calchas, Prophet of Apollo: power 3 -> 2",
   "objective": 0.021283314237983485,
   "deck_term": 0.009170565085022645,
   "card_term": 0.01211274915296084,
   "win_rates": {
    "epic_of_gilgamesh": 0.5099502487562189,
    "inannas_descent": 0.5472636815920398,
    "the_flood": 0.42039800995024873,
    "siege_of_troy": 0.5223880597014925
   }
  }
 ],
 "validation": {
  "objective": 0.04472083420069505,
  "deck_term": 0.02668888888888887,
  "card_term": 0.018031945311806182,
  "win_rates": {
   "epic_of_gilgamesh": 0.4,
   "inannas_descent": 0.5366666666666666,
   "the_flood": 0.6133333333333333,
   "siege_of_troy": 0.45
  }
 }
}